ietk/__init__.py
ietk/metric.py
ietk/util.py
ietk/data/__init__.py
ietk/data/idrid.py
ietk/methods/__init__.py
ietk/methods/brighten_darken_iciar2020.py
ietk/methods/competing_methods.py
ietk/methods/dehaze.py
ietk/methods/illuminate_sharpen.py
ietk/methods/msrcr.py
ietk/methods/sharpen_img.py
IETK_Ret-0.1.1.dist-info/LICENSE
IETK_Ret-0.1.1.dist-info/METADATA
IETK_Ret-0.1.1.dist-info/WHEEL
IETK_Ret-0.1.1.dist-info/top_level.txt
IETK_Ret-0.1.1.dist-info/RECORD
