Metadata-Version: 2.1
Name: IETK-Ret
Version: 0.1.1
Summary: Image Enhancement Toolkit for Retinal Fundus Images IETK-Ret
Home-page: https://github.com/adgaudio/ietk-ret
Author: Alex Gaudio
License: UNKNOWN
Platform: UNKNOWN
Classifier: License :: OSI Approved :: Apache Software License
Classifier: Programming Language :: Python :: 3.8
Requires-Dist: argparse
Requires-Dist: opencv-python
Requires-Dist: opencv-contrib-python
Requires-Dist: matplotlib
Requires-Dist: numpy
Requires-Dist: pillow
Requires-Dist: scikit-image
Requires-Dist: scipy
